jdtt/__init__.py
jdtt/__main__.py
jdtt/exceptions.py
jdtt/schema.py
jdtt/transcompilation/__init__.py
jdtt/transcompilation/_schemas_to_language.py
jdtt/transcompilation/_transcompilation.py
jdtt-1.2.5.dist-info/LICENSE
jdtt-1.2.5.dist-info/METADATA
jdtt-1.2.5.dist-info/WHEEL
jdtt-1.2.5.dist-info/entry_points.txt
jdtt-1.2.5.dist-info/top_level.txt
jdtt-1.2.5.dist-info/RECORD
